Workbook

Sheet Client Invoice
A1: LARIAT BANQUET INVOICE | F1: PRICE LOOKUP TABLE
A2: Client Name: | D2: Event Type: | F2: Item Name | G2: Unit Price
A3: Event Date: | D3: Contact: | F3: Mini Rellenos | G3: 3.5
A4: Guest Count: | D4: Phone: | F4: Corn Dogs | G4: 2
F5: Mac Balls | G5: 2.5
A6: Item Name | B6: Unit Cost | C6: Quantity | D6: Total | E6: Notes | F6: Deviled Eggs | G6: 2
B7: =IFNA(VLOOKUP(A7,F$2:G$100,2,FALSE),"") | D7: =IF(AND(B7<>"",C7<>""),B7*C7,"") | F7: Caprese Skewers | G7: 3
B8: =IFNA(VLOOKUP(A8,F$2:G$100,2,FALSE),"") | D8: =IF(AND(B8<>"",C8<>""),B8*C8,"") | F8: Pig Wings | G8: 4
B9: =IFNA(VLOOKUP(A9,F$2:G$100,2,FALSE),"") | D9: =IF(AND(B9<>"",C9<>""),B9*C9,"") | F9: Nashville Hot Chicken Sliders | G9: 5
B10: =IFNA(VLOOKUP(A10,F$2:G$100,2,FALSE),"") | D10: =IF(AND(B10<>"",C10<>""),B10*C10,"") | F10: Lariat Burger Sliders | G10: 4.5
B11: =IFNA(VLOOKUP(A11,F$2:G$100,2,FALSE),"") | D11: =IF(AND(B11<>"",C11<>""),B11*C11,"") | F11: Battered Avocado Tacos | G11: 4
B12: =IFNA(VLOOKUP(A12,F$2:G$100,2,FALSE),"") | D12: =IF(AND(B12<>"",C12<>""),B12*C12,"") | F12: Carnitas Tacos | G12: 4.5
B13: =IFNA(VLOOKUP(A13,F$2:G$100,2,FALSE),"") | D13: =IF(AND(B13<>"",C13<>""),B13*C13,"") | F13: Barbacoa Tacos | G13: 5
B14: =IFNA(VLOOKUP(A14,F$2:G$100,2,FALSE),"") | D14: =IF(AND(B14<>"",C14<>""),B14*C14,"") | F14: Fish Tacos | G14: 5.5
B15: =IFNA(VLOOKUP(A15,F$2:G$100,2,FALSE),"") | D15: =IF(AND(B15<>"",C15<>""),B15*C15,"") | F15: Green Chile Mac | G15: 6
B16: =IFNA(VLOOKUP(A16,F$2:G$100,2,FALSE),"") | D16: =IF(AND(B16<>"",C16<>""),B16*C16,"") | F16: Rope Caesar Salad | G16: 5
B17: =IFNA(VLOOKUP(A17,F$2:G$100,2,FALSE),"") | D17: =IF(AND(B17<>"",C17<>""),B17*C17,"") | F17: Cobb Salad | G17: 6.5
B18: =IFNA(VLOOKUP(A18,F$2:G$100,2,FALSE),"") | D18: =IF(AND(B18<>"",C18<>""),B18*C18,"") | F18: Coleslaw | G18: 3
... B26: =IFNA(VLOOKUP(A26,F$2:G$100,2,FALSE),"") | D26: =IF(AND(B26<>"",C26<>""),B26*C26,"") | F26: Aji Verde | G26: 1
F27: Alabama White Sauce | G27: 1
C28: Subtotal: | D28: =SUM(D7:D26) | F28: Tartar Sauce | G28: 1
C29: Tax (8.15%): | D29: =D28*0.0815 | F29: Special Sauce | G29: 1
C30: Service Fee (20%): | D30: =D28*0.20 | F30: Santa Fe Caesar Dressing | G30: 1
C31: TOTAL: | D31: =D28+D29+D30 | F31: Buttermilk Brine (per gallon) | G31: 8
F32: Lariat Rub (per batch) | G32: 5
C33: Minimum Spend: | F33: Nashville Hot Rub (per batch) | G33: 6
C34: Over/Under Minimum: | D34: =IF(D33<>"",D28-D33,"")

Sheet Kitchen Prep Sheet
A1: KITCHEN PREP SHEET
A3: Item Name | B3: Quantity | C3: Prep Day | D3: Pre-Prep Tasks | E3: Plating Instructions | F3: Time to Serve | G3: Notes
A4: ='Client Invoice'!A7 | B4: ='Client Invoice'!C7
A5: ='Client Invoice'!A8 | B5: ='Client Invoice'!C8
A6: ='Client Invoice'!A9 | B6: ='Client Invoice'!C9
A7: ='Client Invoice'!A10 | B7: ='Client Invoice'!C10
A8: ='Client Invoice'!A11 | B8: ='Client Invoice'!C11
A9: ='Client Invoice'!A12 | B9: ='Client Invoice'!C12
A10: ='Client Invoice'!A13 | B10: ='Client Invoice'!C13
A11: ='Client Invoice'!A14 | B11: ='Client Invoice'!C14
A12: ='Client Invoice'!A15 | B12: ='Client Invoice'!C15
A13: ='Client Invoice'!A16 | B13: ='Client Invoice'!C16
A14: ='Client Invoice'!A17 | B14: ='Client Invoice'!C17
A15: ='Client Invoice'!A18 | B15: ='Client Invoice'!C18
... A23: ='Client Invoice'!A26 | B23: ='Client Invoice'!C26
A25: PREP DAY OPTIONS: Thursday (braises, stocks), Friday (final prep), Saturday (service prep)
